<?xml version="1.0" encoding="UTF-8"?>
<beans xmlns="http://www.springframework.org/schema/beans"
	xmlns:xsi="http://www.w3.org/2001/XMLSchema-instance"
	xsi:schemaLocation="http://www.springframework.org/schema/beans
                           http://www.springframework.org/schema/beans/spring-beans.xsd">

	<bean id="applicationConfiguration" class="uk.org.taverna.platform.configuration.app.impl.ApplicationConfigurationImpl" />
	<bean id="configurationManager" class="uk.org.taverna.platform.configuration.impl.ConfigurationManagerImpl" >
		<constructor-arg name="applicationConfiguration">
			<ref local="applicationConfiguration" />
		</constructor-arg>
	</bean>
	<!-- <bean id="log4JConfiguration" class="uk.org.taverna.platform.configuration.app.impl.Log4JConfiguration">
		<property name="applicationConfiguration">
			<ref local="applicationConfiguration" />
		</property>
	</bean> -->

</beans>
